MANIFEST.in
README.md
setup.cfg
setup.py
metadir/__init__.py
metadir/cli.py
metadir/commands/__init__.py
metadir/commands/base.py
metadir/commands/init.py
metadir/commands/utils.py
tests/test_cli.py
tests/__pycache__/test_cli.cpython-36-PYTEST.pyc
tests/commands/test_hello.py
tests/commands/__pycache__/test_hello.cpython-36-PYTEST.pyc